qabbage/__init__.py
qabbage/client.py
qabbage-0.0.1.dist-info/METADATA
qabbage-0.0.1.dist-info/WHEEL
qabbage-0.0.1.dist-info/RECORD
