Metadata-Version: 2.4
Name: qabbage
Version: 0.0.1
Summary: Qabbage client SDK (thin client)
Requires-Python: >=3.10
Requires-Dist: httpx>=0.27.0
